odoo/addons/product_category_hr_department/README.rst
odoo/addons/product_category_hr_department/__init__.py
odoo/addons/product_category_hr_department/__manifest__.py
odoo/addons/product_category_hr_department/i18n/es.po
odoo/addons/product_category_hr_department/i18n/it.po
odoo/addons/product_category_hr_department/i18n/product_category_hr_department.pot
odoo/addons/product_category_hr_department/models/__init__.py
odoo/addons/product_category_hr_department/models/product_category.py
odoo/addons/product_category_hr_department/readme/CONTRIBUTORS.rst
odoo/addons/product_category_hr_department/readme/DESCRIPTION.rst
odoo/addons/product_category_hr_department/static/description/icon.png
odoo/addons/product_category_hr_department/static/description/index.html
odoo/addons/product_category_hr_department/views/product_category_views.xml
odoo_addon_product_category_hr_department-16.0.1.0.0.7.dist-info/METADATA
odoo_addon_product_category_hr_department-16.0.1.0.0.7.dist-info/WHEEL
odoo_addon_product_category_hr_department-16.0.1.0.0.7.dist-info/top_level.txt
odoo_addon_product_category_hr_department-16.0.1.0.0.7.dist-info/RECORD
